kusto_tool/__init__.py
kusto_tool/__main__.py
kusto_tool/database.py
kusto_tool/expression.py
kusto_tool/function.py
kusto_tool-0.4.2.dist-info/LICENSE
kusto_tool-0.4.2.dist-info/WHEEL
kusto_tool-0.4.2.dist-info/METADATA
kusto_tool-0.4.2.dist-info/RECORD
