Metadata-Version: 2.1
Name: kusto-tool
Version: 0.4.2
Summary: A high-level API for querying Kusto.
Author-email: Alex Kyllo <alex.kyllo@gmail.com>
Classifier: License :: OSI Approved :: MIT License
Requires-Dist: azure-kusto-data
Requires-Dist: loguru
Requires-Dist: Jinja2
Requires-Dist: pandas
Requires-Dist: azure-cli ; extra == "azure-cli"
Requires-Dist: black ; extra == "dev"
Requires-Dist: pylint ; extra == "dev"
Requires-Dist: furo ; extra == "doc"
Requires-Dist: sphinx ; extra == "doc"
Requires-Dist: sphinx-autobuild ; extra == "doc"
Requires-Dist: sphinx_rtd_theme ; extra == "doc"
Requires-Dist: pytest ; extra == "test"
Requires-Dist: nox ; extra == "test"
Requires-Dist: coverage ; extra == "test"
Requires-Dist: pytest-cov ; extra == "test"
Requires-Dist: pytest-mock ; extra == "test"
Project-URL: Home, https://github.com/alexkyllo/kusto-tool
Provides-Extra: azure-cli
Provides-Extra: dev
Provides-Extra: doc
Provides-Extra: test
